{
    "thn": {
        "zero two": -20,
        "zero three": -20,
        "five two": -40,
        "three two": -30,
        "four three": -50,
        "three four": -40,
        "five one": -50,
        "five four": -60,
        "seven five": -40,
        "six one": -70,
        "one six": 20,
        "six two": -40,
        "seven four": -80,
        "seven zero": -40,
        "seven eight": -40,
        "eight seven": -40,
        "eight two": -50,
        "five nine": -70,
        "six nine": -70,
        "nine seven": -40,
        "seven nine": -20,
        "eight nine": -20,
        "@_D @_I": -60,
        "@_D @_J": -60,
        "@_S @_Z": -40,
        "@_O @_I": -50,
        "@_Omicron @_Iota": -50,
        "@_Psi @_Iota": -40,
        "@_b @_j": -60,
        "@_f @_a": -70,
        "@_o @_j": -50,
        "@_m @_j": -50,
        "@_a @_j": -60,
        "@_e @_x": -30,
        "@_e @_j": -50,
        "@_o @_j": -60,
        "@_Alpha @_alpha": -40,
        "@_gamma @_alpha": -40,
        "@_chi @_beta": -40,
        "@_xi @_alpha": -40,
        "@_xi @_omicron": -40,
        "@_xi @_sigma": -30,
        "@_gamma @_theta": -30,
        "@_gamma sigma1": -40,
        "@_gamma @_rho": -30,
        "@_gamma @_sigma": -50,
        "@_gamma @_omega": -30,
        "@_sigma @_Alpha": 50,
        "@_gamma @_omicron": -40,
        "@_kappa @_nu": -60,
        "@_kappa @_omega": -40,
        "@_Alpha @_xi": -40,
        "@_xi @_omega": -30,
        "@_chi @_mugreek": -50,
        "@_kappa @_delta": -40,
        "@_Omicron @_Xi": -50
    },
    "reg": {
        "zero two": -20,
        "zero three": -20,
        "five two": -40,
        "three two": -30,
        "four three": -50,
        "three four": -40,
        "five one": -50,
        "five four": -60,
        "seven five": -40,
        "six one": -70,
        "one six": 20,
        "six two": -40,
        "seven four": -80,
        "seven zero": -40,
        "seven eight": -40,
        "eight seven": -40,
        "eight two": -50,
        "five nine": -70,
        "six nine": -70,
        "nine seven": -40,
        "seven nine": -20,
        "eight nine": -20,
        "@_D @_I": -60,
        "@_D @_J": -60,
        "@_S @_Z": -40,
        "@_O @_I": -50,
        "@_Omicron @_Iota": -50,
        "@_Psi @_Iota": -40,
        "@_b @_j": -60,
        "@_f @_a": -70,
        "@_o @_j": -50,
        "@_m @_j": -50,
        "@_a @_j": -60,
        "@_e @_x": -30,
        "@_e @_j": -50,
        "@_o @_j": -60,
        "@_Alpha @_alpha": -40,
        "@_gamma @_alpha": -40,
        "@_chi @_beta": -40,
        "@_xi @_alpha": -40,
        "@_xi @_omicron": -40,
        "@_xi @_sigma": -30,
        "@_gamma @_theta": -30,
        "@_gamma sigma1": -40,
        "@_gamma @_rho": -30,
        "@_gamma @_sigma": -50,
        "@_gamma @_omega": -30,
        "@_sigma @_Alpha": 50,
        "@_gamma @_omicron": -40,
        "@_kappa @_nu": -60,
        "@_kappa @_omega": -40,
        "@_Alpha @_xi": -40,
        "@_xi @_omega": -30,
        "@_chi @_mugreek": -50,
        "@_kappa @_delta": -40,
        "@_Omicron @_Xi": -50
    },
    "bld": {
        "zero two": -20,
        "zero three": -20,
        "five two": -40,
        "three two": -30,
        "four three": -50,
        "three four": -40,
        "five one": -50,
        "five four": -60,
        "seven five": -40,
        "six one": -70,
        "one six": 20,
        "six two": -40,
        "seven four": -80,
        "seven zero": -40,
        "seven eight": -40,
        "eight seven": -40,
        "eight two": -50,
        "five nine": -70,
        "six nine": -70,
        "nine seven": -40,
        "seven nine": -20,
        "eight nine": -20,
        "@_D @_I": -60,
        "@_D @_J": -60,
        "@_S @_Z": -40,
        "@_O @_I": -50,
        "@_Omicron @_Iota": -50,
        "@_Psi @_Iota": -40,
        "@_b @_j": -60,
        "@_f @_a": -70,
        "@_o @_j": -50,
        "@_m @_j": -50,
        "@_a @_j": -60,
        "@_e @_x": -30,
        "@_e @_j": -50,
        "@_o @_j": -60,
        "@_Alpha @_alpha": -40,
        "@_gamma @_alpha": -40,
        "@_chi @_beta": -40,
        "@_xi @_alpha": -40,
        "@_xi @_omicron": -40,
        "@_xi @_sigma": -30,
        "@_gamma @_theta": -30,
        "@_gamma sigma1": -40,
        "@_gamma @_rho": -30,
        "@_gamma @_sigma": -50,
        "@_gamma @_omega": -30,
        "@_sigma @_Alpha": 50,
        "@_gamma @_omicron": -40,
        "@_kappa @_nu": -60,
        "@_kappa @_omega": -40,
        "@_Alpha @_xi": -40,
        "@_xi @_omega": -30,
        "@_chi @_mugreek": -50,
        "@_kappa @_delta": -40,
        "@_Omicron @_Xi": -50
    },
    "thn_it": {
        "zero two": -20,
        "zero three": -20,
        "five two": -40,
        "three two": -30,
        "four three": -50,
        "three four": -40,
        "five one": -50,
        "five four": -60,
        "seven five": -40,
        "six one": -70,
        "one six": 20,
        "six two": -40,
        "seven four": -80,
        "seven zero": -40,
        "seven eight": -40,
        "eight seven": -40,
        "eight two": -50,
        "five nine": -70,
        "six nine": -70,
        "nine seven": -40,
        "seven nine": -20,
        "eight nine": -20,
        "@_D @_I": -60,
        "@_D @_J": -60,
        "@_S @_Z": -40,
        "@_O @_I": -50,
        "@_Omicron @_Iota": -50,
        "@_Psi @_Iota": -40,
        "@_b @_j": -60,
        "@_f @_a": -70,
        "@_o @_j": -50,
        "@_m @_j": -50,
        "@_a @_j": -60,
        "@_e @_x": -30,
        "@_e @_j": -50,
        "@_o @_j": -60,
        "@_Alpha @_alpha": -40,
        "@_gamma @_alpha": -40,
        "@_chi @_beta": -40,
        "@_xi @_alpha": -40,
        "@_xi @_omicron": -40,
        "@_xi @_sigma": -30,
        "@_gamma @_theta": -30,
        "@_gamma sigma1": -40,
        "@_gamma @_rho": -30,
        "@_gamma @_sigma": -50,
        "@_gamma @_omega": -30,
        "@_sigma @_Alpha": 50,
        "@_gamma @_omicron": -40,
        "@_kappa @_nu": -60,
        "@_kappa @_omega": -40,
        "@_Alpha @_xi": -40,
        "@_xi @_omega": -30,
        "@_chi @_mugreek": -50,
        "@_kappa @_delta": -40,
        "@_Omicron @_Xi": -50
    },
    "reg_it": {
        "zero two": -20,
        "zero three": -20,
        "five two": -40,
        "three two": -30,
        "four three": -50,
        "three four": -40,
        "five one": -50,
        "five four": -60,
        "seven five": -40,
        "six one": -70,
        "one six": 20,
        "six two": -40,
        "seven four": -80,
        "seven zero": -40,
        "seven eight": -40,
        "eight seven": -40,
        "eight two": -50,
        "five nine": -70,
        "six nine": -70,
        "nine seven": -40,
        "seven nine": -20,
        "eight nine": -20,
        "@_D @_I": -60,
        "@_D @_J": -60,
        "@_S @_Z": -40,
        "@_O @_I": -50,
        "@_Omicron @_Iota": -50,
        "@_Psi @_Iota": -40,
        "@_b @_j": -60,
        "@_f @_a": -70,
        "@_o @_j": -50,
        "@_m @_j": -50,
        "@_a @_j": -60,
        "@_e @_x": -30,
        "@_e @_j": -50,
        "@_o @_j": -60,
        "@_Alpha @_alpha": -40,
        "@_gamma @_alpha": -40,
        "@_chi @_beta": -40,
        "@_xi @_alpha": -40,
        "@_xi @_omicron": -40,
        "@_xi @_sigma": -30,
        "@_gamma @_theta": -30,
        "@_gamma sigma1": -40,
        "@_gamma @_rho": -30,
        "@_gamma @_sigma": -50,
        "@_gamma @_omega": -30,
        "@_sigma @_Alpha": 50,
        "@_gamma @_omicron": -40,
        "@_kappa @_nu": -60,
        "@_kappa @_omega": -40,
        "@_Alpha @_xi": -40,
        "@_xi @_omega": -30,
        "@_chi @_mugreek": -50,
        "@_kappa @_delta": -40,
        "@_Omicron @_Xi": -50
    },
    "bld_it": {
        "zero two": -20,
        "zero three": -20,
        "five two": -40,
        "three two": -30,
        "four three": -50,
        "three four": -40,
        "five one": -50,
        "five four": -60,
        "seven five": -40,
        "six one": -70,
        "one six": 20,
        "six two": -40,
        "seven four": -80,
        "seven zero": -40,
        "seven eight": -40,
        "eight seven": -40,
        "eight two": -50,
        "five nine": -70,
        "six nine": -70,
        "nine seven": -40,
        "seven nine": -20,
        "eight nine": -20,
        "@_D @_I": -60,
        "@_D @_J": -60,
        "@_S @_Z": -40,
        "@_O @_I": -50,
        "@_Omicron @_Iota": -50,
        "@_Psi @_Iota": -40,
        "@_b @_j": -60,
        "@_f @_a": -70,
        "@_o @_j": -50,
        "@_m @_j": -50,
        "@_a @_j": -60,
        "@_e @_x": -30,
        "@_e @_j": -50,
        "@_o @_j": -60,
        "@_Alpha @_alpha": -40,
        "@_gamma @_alpha": -40,
        "@_chi @_beta": -40,
        "@_xi @_alpha": -40,
        "@_xi @_omicron": -40,
        "@_xi @_sigma": -30,
        "@_gamma @_theta": -30,
        "@_gamma sigma1": -40,
        "@_gamma @_rho": -30,
        "@_gamma @_sigma": -50,
        "@_gamma @_omega": -30,
        "@_sigma @_Alpha": 50,
        "@_gamma @_omicron": -40,
        "@_kappa @_nu": -60,
        "@_kappa @_omega": -40,
        "@_Alpha @_xi": -40,
        "@_xi @_omega": -30,
        "@_chi @_mugreek": -50,
        "@_kappa @_delta": -40,
        "@_Omicron @_Xi": -50
    }
}